gen_regex/__init__.py
gen_regex/core.py
gen_regex/test.py
gen_regex-0.1.4.dist-info/METADATA
gen_regex-0.1.4.dist-info/WHEEL
gen_regex-0.1.4.dist-info/RECORD
