Metadata-Version: 2.1
Name: gen-regex
Version: 0.1.4
Summary: Generate regex from a list of strings
Author-email: Momo1122 <39585852+imoken1122@users.noreply.github.com>
Requires-Python: >=3.7
Requires-Dist: gen-regex>=0.1.2
Requires-Dist: pytest>=7.4.2
Requires-Dist: regex>=2023.10.3
